{
  "project_info": {
    "project_number": "386609602692",
    "project_id": "quick-quiz-app-63f12",
    "storage_bucket": "quick-quiz-app-63f12.appspot.com"
  },
  "client": [
    {
      "client_info": {
        "mobilesdk_app_id": "1:386609602692:android:aca2944f9f35d17931a2d1",
        "android_client_info": {
          "package_name": "com.example.quiz_app"
        }
      },
      "oauth_client": [
        {
          "client_id": "386609602692-1d1s4ohpcrnqgn5odhrbfrqt9br963ss.apps.googleusercontent.com",
          "client_type": 3
        }
      ],
      "api_key": [
        {
          "current_key": ""
        }
      ],
      "services": {
        "appinvite_service": {
          "other_platform_oauth_client": [
            {
              "client_id": "386609602692-1d1s4ohpcrnqgn5odhrbfrqt9br963ss.apps.googleusercontent.com",
              "client_type": 3
            }
          ]
        }
      }
    }
  ],
  "configuration_version": "1"
}